generate_gitignore/__init__.py
generate_gitignore/cache.py
generate_gitignore/main.py
generate_gitignore/search.py
generate_gitignore/version.py
generate_gitignore-1.0.2.dist-info/LICENSE
generate_gitignore-1.0.2.dist-info/METADATA
generate_gitignore-1.0.2.dist-info/WHEEL
generate_gitignore-1.0.2.dist-info/entry_points.txt
generate_gitignore-1.0.2.dist-info/top_level.txt
generate_gitignore-1.0.2.dist-info/RECORD
