Metadata-Version: 2.1
Name: generate-gitignore
Version: 1.0.2
Summary: A CLI tool for generating .gitignore files
Home-page: https://github.com/kristiankunc/generate-gitignore
Author: Kristián Kunc
Author-email: kristian@kristn.co.uk
Classifier: Programming Language :: Python :: 3
Classifier: License :: OSI Approved :: MIT License
Classifier: Operating System :: OS Independent
Requires-Python: >=3.7
License-File: LICENSE
Requires-Dist: requests
Requires-Dist: argparse
Requires-Dist: colorama
Requires-Dist: platformdirs
